homogeneous_segmentation/__init__.py
homogeneous_segmentation/_cumulative_p.py
homogeneous_segmentation/_cumulative_q.py
homogeneous_segmentation/_optimal_bisections.py
homogeneous_segmentation/_seg_mcv.py
homogeneous_segmentation/_seg_shs.py
homogeneous_segmentation-2.1.0.dist-info/METADATA
homogeneous_segmentation-2.1.0.dist-info/WHEEL
homogeneous_segmentation-2.1.0.dist-info/RECORD
