Metadata-Version: 2.1
Name: homogeneous-segmentation
Version: 2.1.0
Summary: Methods for homogenous segmentation of linear spatial data, such as pavement performance indicators and traffic volumes. Two of the three original methods have been ported; the spatial heterogeneity based segmentation, and the Minimise Coefficient of Variation segmentation. The original R package also implmented the cumulative difference approach and a number of associated functions not ported to thise package.
Project-URL: Homepage, https://github.com/thehappycheese/homogeneous-segmentation
Project-URL: Original R Package, https://cran.r-project.org/web/packages/HS/index.html
Author: Yongze Song, Nicholas Archer
License-Expression: GPL-2.0-only
Requires-Python: >=3.9
Requires-Dist: pandas
Provides-Extra: dev
Requires-Dist: pytest; extra == 'dev'
